[
  {
    "id": "CUST-001",
    "name": "Amina Mwangi",
    "email": "amina.mwangi@techsolutions.ke",
    "company": "TechSolutions Kenya Ltd",
    "industry": "Technology",
    "country": "Kenya",
    "status": "Active",
    "tier": "Premium",
    "createdDate": "2023-03-12T00:00:00Z",
    "totalSpent": 14388.00,
    "monthlyRecurringRevenue": 1199.00,
    "healthScore": 92.5
  },
  {
    "id": "CUST-002",
    "name": "Bongani Dlamini",
    "email": "bongani@nkosi-construction.co.za",
    "company": "Nkosi Construction Group",
    "industry": "Manufacturing",
    "country": "South Africa",
    "status": "Active",
    "tier": "Enterprise",
    "createdDate": "2022-08-01T00:00:00Z",
    "totalSpent": 58320.00,
    "monthlyRecurringRevenue": 2880.00,
    "healthScore": 88.0
  },
  {
    "id": "CUST-003",
    "name": "Nadia El-Sayed",
    "email": "nadia@cairo-ventures.com.eg",
    "company": "Cairo Ventures Capital",
    "industry": "Finance",
    "country": "Egypt",
    "status": "Active",
    "tier": "Professional",
    "createdDate": "2023-11-20T00:00:00Z",
    "totalSpent": 4788.00,
    "monthlyRecurringRevenue": 599.00,
    "healthScore": 78.5
  },
  {
    "id": "CUST-004",
    "name": "Kwabena Asante",
    "email": "k.asante@goldcoast-distribution.com.gh",
    "company": "GoldCoast Distribution Ltd",
    "industry": "Retail",
    "country": "Ghana",
    "status": "Active",
    "tier": "Professional",
    "createdDate": "2023-05-15T00:00:00Z",
    "totalSpent": 9588.00,
    "monthlyRecurringRevenue": 599.00,
    "healthScore": 85.0
  },
  {
    "id": "CUST-005",
    "name": "Sade Okafor",
    "email": "sade.okafor@lagosbiz.com.ng",
    "company": "Lagos Business Services",
    "industry": "Finance",
    "country": "Nigeria",
    "status": "Active",
    "tier": "Premium",
    "createdDate": "2022-12-01T00:00:00Z",
    "totalSpent": 28680.00,
    "monthlyRecurringRevenue": 1199.00,
    "healthScore": 94.0
  },
  {
    "id": "CUST-006",
    "name": "Mutale Banda",
    "email": "m.banda@copperbelt-mining.com.zm",
    "company": "Copperbelt Mining Supplies",
    "industry": "Manufacturing",
    "country": "Zambia",
    "status": "Active",
    "tier": "Enterprise",
    "createdDate": "2023-01-10T00:00:00Z",
    "totalSpent": 43200.00,
    "monthlyRecurringRevenue": 2880.00,
    "healthScore": 72.0
  },
  {
    "id": "CUST-007",
    "name": "Thabo Nkosi",
    "email": "thabo@savannahlogistics.co.za",
    "company": "Savannah Logistics SA",
    "industry": "Manufacturing",
    "country": "South Africa",
    "status": "Active",
    "tier": "Professional",
    "createdDate": "2024-02-14T00:00:00Z",
    "totalSpent": 5987.00,
    "monthlyRecurringRevenue": 599.00,
    "healthScore": 81.0
  },
  {
    "id": "CUST-008",
    "name": "Grace Owusu",
    "email": "grace.owusu@owusu-trading.com.gh",
    "company": "Owusu Trading Company",
    "industry": "Retail",
    "country": "Ghana",
    "status": "Active",
    "tier": "Starter",
    "createdDate": "2024-06-01T00:00:00Z",
    "totalSpent": 1197.00,
    "monthlyRecurringRevenue": 199.00,
    "healthScore": 65.0
  },
  {
    "id": "CUST-009",
    "name": "Emeka Nwosu",
    "email": "emeka@nwosu-consulting.com.ng",
    "company": "Nwosu Management Consulting",
    "industry": "Technology",
    "country": "Nigeria",
    "status": "Inactive",
    "tier": "Starter",
    "createdDate": "2023-09-05T00:00:00Z",
    "totalSpent": 2388.00,
    "monthlyRecurringRevenue": 0.00,
    "healthScore": 32.0
  },
  {
    "id": "CUST-010",
    "name": "Aisha Kamara",
    "email": "aisha.k@westerngate-capital.com.sl",
    "company": "WesternGate Capital Partners",
    "industry": "Finance",
    "country": "Nigeria",
    "status": "Active",
    "tier": "Premium",
    "createdDate": "2024-04-22T00:00:00Z",
    "totalSpent": 10791.00,
    "monthlyRecurringRevenue": 1199.00,
    "healthScore": 87.5
  }
]
